{
  "artifact_kind": "suboff_domain_convergence_study",
  "schema": "suboff-domain-convergence-study-r1",
  "status": "diagnostic_only",
  "physical_validation": false,
  "domain_levels": [
    {
      "level_id": "domain_48",
      "nx": 48,
      "ny": 24,
      "nz": 24,
      "domain_length_lu": 48.0,
      "blockage_ratio": 0.010693705940064569
    },
    {
      "level_id": "domain_64",
      "nx": 64,
      "ny": 32,
      "nz": 32,
      "domain_length_lu": 64.0,
      "blockage_ratio": 0.00601520959128632
    },
    {
      "level_id": "domain_80",
      "nx": 80,
      "ny": 40,
      "nz": 40,
      "domain_length_lu": 80.0,
      "blockage_ratio": 0.0038497341384232447
    }
  ],
  "Ct_per_level": [
    0.4899851693578564,
    0.4852150715482962,
    0.4818580196979298
  ],
  "convergence_indicator": {
    "relative_ct_changes": [
      0.009735188140105575,
      0.006918688324445919
    ],
    "ct_trend": "decreasing",
    "max_relative_change": 0.009735188140105575,
    "convergence_claim": "withheld",
    "note": "Relative Ct changes across domain sizes are diagnostic indicators only; they do not constitute a domain convergence claim or physical validation."
  },
  "per_level_results": [
    {
      "level_id": "domain_48",
      "nx": 48,
      "ny": 24,
      "nz": 24,
      "domain_length_lu": 48.0,
      "hull_length_lu": 24.0,
      "hull_radius_lu": 1.4002333722287048,
      "blockage_ratio": 0.010693705940064569,
      "Ct": 0.4899851693578564,
      "ct_mean": 0.4899851693578564,
      "ct_time_series": [
        {
          "step": 1,
          "ct": 11.111114457336782,
          "ct_fric": 11.041496079741863,
          "ct_pres": 0.06961837759491993
        },
        {
          "step": 2,
          "ct": -3.67192198260187,
          "ct_fric": -3.8285396601024426,
          "ct_pres": 0.15661767750057262
        },
        {
          "step": 3,
          "ct": 1.924447248454082,
          "ct_fric": 1.7702688269298477,
          "ct_pres": 0.15417842152423428
        },
        {
          "step": 4,
          "ct": 1.1188483975186583,
          "ct_fric": 0.9868519945550981,
          "ct_pres": 0.13199640296356022
        },
        {
          "step": 5,
          "ct": -0.5349758374461953,
          "ct_fric": -0.6394891213056139,
          "ct_pres": 0.10451328385941865
        },
        {
          "step": 6,
          "ct": 2.1584719145606734,
          "ct_fric": 2.0958699010555306,
          "ct_pres": 0.06260201350514254
        },
        {
          "step": 7,
          "ct": -0.26874574105144045,
          "ct_fric": -0.30666867888835236,
          "ct_pres": 0.037922937836911946
        },
        {
          "step": 8,
          "ct": 0.5117823107599117,
          "ct_fric": 0.49211008205026413,
          "ct_pres": 0.019672228709647528
        },
        {
          "step": 9,
          "ct": 0.7845923217416507,
          "ct_fric": 0.7755473452957102,
          "ct_pres": 0.009044976445940404
        },
        {
          "step": 10,
          "ct": 0.15404688485383788,
          "ct_fric": 0.14695781662378618,
          "ct_pres": 0.007089068230051693
        },
        {
          "step": 11,
          "ct": 0.5975422903011517,
          "ct_fric": 0.5899188378141103,
          "ct_pres": 0.007623452487041428
        },
        {
          "step": 12,
          "ct": 0.3570243529508586,
          "ct_fric": 0.34745229713917525,
          "ct_pres": 0.009572055811683336
        },
        {
          "step": 13,
          "ct": 0.35568187908022825,
          "ct_fric": 0.34388900697915975,
          "ct_pres": 0.011792872101068497
        },
        {
          "step": 14,
          "ct": 0.46985888341714066,
          "ct_fric": 0.4568644982133194,
          "ct_pres": 0.01299438520382122
        },
        {
          "step": 15,
          "ct": 0.33549099239390795,
          "ct_fric": 0.32128891152926503,
          "ct_pres": 0.014202080864642896
        },
        {
          "step": 16,
          "ct": 0.39232006248276535,
          "ct_fric": 0.37722627721017316,
          "ct_pres": 0.015093785272592192
        },
        {
          "step": 17,
          "ct": 0.38855854630370684,
          "ct_fric": 0.37175533964719587,
          "ct_pres": 0.016803206656510968
        },
        {
          "step": 18,
          "ct": 0.3509184870006845,
          "ct_fric": 0.33116720868904787,
          "ct_pres": 0.019751278311636613
        },
        {
          "step": 19,
          "ct": 0.3987824608110445,
          "ct_fric": 0.37480433181289247,
          "ct_pres": 0.023978128998152097
        },
        {
          "step": 20,
          "ct": 0.3634518947617253,
          "ct_fric": 0.3344441336908735,
          "ct_pres": 0.029007761070851793
        }
      ],
      "force_time_series": [
        {
          "step": 1,
          "fx": 5.320001602172852,
          "fy": 4.76837158203125e-07,
          "fz": 0.0
        },
        {
          "step": 2,
          "fx": -1.7581162452697754,
          "fy": 1.430511474609375e-06,
          "fz": 2.86102294921875e-06
        },
        {
          "step": 3,
          "fx": 0.9214253425598145,
          "fy": -9.5367431640625e-07,
          "fz": 9.5367431640625e-07
        },
        {
          "step": 4,
          "fx": 0.5357046127319336,
          "fy": 1.430511474609375e-06,
          "fz": 1.9073486328125e-06
        },
        {
          "step": 5,
          "fx": -0.2561464309692383,
          "fy": 9.5367431640625e-07,
          "fz": 3.337860107421875e-06
        },
        {
          "step": 6,
          "fx": 1.0334763526916504,
          "fy": 1.9073486328125e-06,
          "fz": 1.9073486328125e-06
        },
        {
          "step": 7,
          "fx": -0.1286754608154297,
          "fy": -9.5367431640625e-07,
          "fz": -2.384185791015625e-06
        },
        {
          "step": 8,
          "fx": 0.2450413703918457,
          "fy": -1.9073486328125e-06,
          "fz": 4.291534423828125e-06
        },
        {
          "step": 9,
          "fx": 0.37566280364990234,
          "fy": 3.337860107421875e-06,
          "fz": -9.5367431640625e-07
        },
        {
          "step": 10,
          "fx": 0.07375764846801758,
          "fy": 2.384185791015625e-06,
          "fz": 4.76837158203125e-07
        },
        {
          "step": 11,
          "fx": 0.2861032485961914,
          "fy": -6.67572021484375e-06,
          "fz": -7.62939453125e-06
        },
        {
          "step": 12,
          "fx": 0.1709432601928711,
          "fy": -3.337860107421875e-05,
          "fz": -3.147125244140625e-05
        },
        {
          "step": 13,
          "fx": 0.17030048370361328,
          "fy": -0.00014543533325195312,
          "fz": -0.00015163421630859375
        },
        {
          "step": 14,
          "fx": 0.22496843338012695,
          "fy": -0.0003261566162109375,
          "fz": -0.0003046989440917969
        },
        {
          "step": 15,
          "fx": 0.16063308715820312,
          "fy": -0.0006561279296875,
          "fz": -0.0006809234619140625
        },
        {
          "step": 16,
          "fx": 0.18784284591674805,
          "fy": -0.0009751319885253906,
          "fz": -0.0009427070617675781
        },
        {
          "step": 17,
          "fx": 0.18604183197021484,
          "fy": -0.0013146400451660156,
          "fz": -0.0013608932495117188
        },
        {
          "step": 18,
          "fx": 0.16801977157592773,
          "fy": -0.0013704299926757812,
          "fz": -0.0013632774353027344
        },
        {
          "step": 19,
          "fx": 0.19093704223632812,
          "fy": -0.0013060569763183594,
          "fz": -0.0013499259948730469
        },
        {
          "step": 20,
          "fx": 0.17402076721191406,
          "fy": -0.0009684562683105469,
          "fz": -0.0009694099426269531
        }
      ],
      "wetted_area": 266.0,
      "dynamic_pressure": 0.4788,
      "evidence_status": "measured_candidate",
      "physical_validation": false,
      "steady_state": "diagnostic_withheld",
      "runtime": {
        "requested_steps": 20,
        "completed_steps": 20,
        "finite_population_checks": 20,
        "finite_density_checks": 20,
        "all_populations_finite": true,
        "all_densities_finite": true,
        "density_min": 0.9302381873130798,
        "density_max": 1.2096786499023438,
        "device": "cpu",
        "tau": 0.5216,
        "nu": 0.0072
      },
      "admission": {
        "status": "skipped",
        "reason": "use_wall_function=False; bounce-back solid boundary only, no wall function admitted"
      },
      "config": {
        "lattice": "D3Q19",
        "collision": "MRT",
        "boundary": "bounce_back",
        "wall": "static",
        "hull_type": "bare_hull",
        "nx": 48,
        "ny": 24,
        "nz": 24,
        "n_steps": 20,
        "warmup": 5,
        "u_in": 0.06,
        "re": 200.0,
        "hull_length": 24.0,
        "use_wall_function": false
      }
    },
    {
      "level_id": "domain_64",
      "nx": 64,
      "ny": 32,
      "nz": 32,
      "domain_length_lu": 64.0,
      "hull_length_lu": 24.0,
      "hull_radius_lu": 1.4002333722287048,
      "blockage_ratio": 0.00601520959128632,
      "Ct": 0.4852150715482962,
      "ct_mean": 0.4852150715482962,
      "ct_time_series": [
        {
          "step": 1,
          "ct": 11.111108481933798,
          "ct_fric": 11.041490104338878,
          "ct_pres": 0.06961837759491993
        },
        {
          "step": 2,
          "ct": -3.6719249703033627,
          "ct_fric": -3.828542647803935,
          "ct_pres": 0.15661767750057262
        },
        {
          "step": 3,
          "ct": 1.9244502361555744,
          "ct_fric": 1.770271799070395,
          "ct_pres": 0.15417843708517956
        },
        {
          "step": 4,
          "ct": 1.1188384385136834,
          "ct_fric": 0.9868420355501231,
          "ct_pres": 0.13199640296356022
        },
        {
          "step": 5,
          "ct": -0.5349818128491802,
          "ct_fric": -0.6394950967085988,
          "ct_pres": 0.10451328385941865
        },
        {
          "step": 6,
          "ct": 2.158474902262166,
          "ct_fric": 2.0958728070620607,
          "ct_pres": 0.06260209520010522
        },
        {
          "step": 7,
          "ct": -0.26874574105144045,
          "ct_fric": -0.30666867888835236,
          "ct_pres": 0.037922937836911946
        },
        {
          "step": 8,
          "ct": 0.5117793230584191,
          "ct_fric": 0.49210717604373433,
          "ct_pres": 0.019672147014684845
        },
        {
          "step": 9,
          "ct": 0.7845903299406557,
          "ct_fric": 0.7755490054540591,
          "ct_pres": 0.009041324486596542
        },
        {
          "step": 10,
          "ct": 0.15403393814737038,
          "ct_fric": 0.14696437215826216,
          "ct_pres": 0.007069565989108213
        },
        {
          "step": 11,
          "ct": 0.5976060279329917,
          "ct_fric": 0.5900413749090636,
          "ct_pres": 0.007564653023928031
        },
        {
          "step": 12,
          "ct": 0.3574904343836887,
          "ct_fric": 0.34807075037556384,
          "ct_pres": 0.009419684008124877
        },
        {
          "step": 13,
          "ct": 0.3538992171897028,
          "ct_fric": 0.3424390167022807,
          "ct_pres": 0.011460200487422066
        },
        {
          "step": 14,
          "ct": 0.4721942700837788,
          "ct_fric": 0.4598734870789543,
          "ct_pres": 0.01232078300482448
        },
        {
          "step": 15,
          "ct": 0.3285256643143911,
          "ct_fric": 0.31559663508071834,
          "ct_pres": 0.012929029233672765
        },
        {
          "step": 16,
          "ct": 0.3959899558160538,
          "ct_fric": 0.38334820302842854,
          "ct_pres": 0.012641752787625282
        },
        {
          "step": 17,
          "ct": 0.37252853189594265,
          "ct_fric": 0.3602039306241717,
          "ct_pres": 0.01232460127177095
        },
        {
          "step": 18,
          "ct": 0.3483102235977313,
          "ct_fric": 0.336343566859849,
          "ct_pres": 0.011966656737882293
        },
        {
          "step": 19,
          "ct": 0.36789958638356146,
          "ct_fric": 0.35613783520048076,
          "ct_pres": 0.011761751183080694
        },
        {
          "step": 20,
          "ct": 0.3436494092694301,
          "ct_fric": 0.3320852616675814,
          "ct_pres": 0.011564147601848656
        }
      ],
      "force_time_series": [
        {
          "step": 1,
          "fx": 5.319998741149902,
          "fy": 1.9073486328125e-06,
          "fz": -9.5367431640625e-07
        },
        {
          "step": 2,
          "fx": -1.75811767578125,
          "fy": 3.814697265625e-06,
          "fz": 2.86102294921875e-06
        },
        {
          "step": 3,
          "fx": 0.9214267730712891,
          "fy": -3.814697265625e-06,
          "fz": -1.9073486328125e-06
        },
        {
          "step": 4,
          "fx": 0.5356998443603516,
          "fy": 1.9073486328125e-06,
          "fz": 0.0
        },
        {
          "step": 5,
          "fx": -0.2561492919921875,
          "fy": 0.0,
          "fz": 9.5367431640625e-07
        },
        {
          "step": 6,
          "fx": 1.033477783203125,
          "fy": -1.9073486328125e-06,
          "fz": -3.814697265625e-06
        },
        {
          "step": 7,
          "fx": -0.1286754608154297,
          "fy": 0.0,
          "fz": -9.5367431640625e-07
        },
        {
          "step": 8,
          "fx": 0.2450399398803711,
          "fy": 0.0,
          "fz": 9.5367431640625e-07
        },
        {
          "step": 9,
          "fx": 0.37566184997558594,
          "fy": 3.814697265625e-06,
          "fz": 0.0
        },
        {
          "step": 10,
          "fx": 0.07375144958496094,
          "fy": 1.9073486328125e-06,
          "fz": 9.5367431640625e-07
        },
        {
          "step": 11,
          "fx": 0.2861337661743164,
          "fy": 0.0,
          "fz": 1.9073486328125e-06
        },
        {
          "step": 12,
          "fx": 0.17116641998291016,
          "fy": 3.814697265625e-06,
          "fz": -9.5367431640625e-07
        },
        {
          "step": 13,
          "fx": 0.1694469451904297,
          "fy": 0.0,
          "fz": 0.0
        },
        {
          "step": 14,
          "fx": 0.22608661651611328,
          "fy": 0.0,
          "fz": -3.814697265625e-06
        },
        {
          "step": 15,
          "fx": 0.15729808807373047,
          "fy": -1.9073486328125e-06,
          "fz": 2.86102294921875e-06
        },
        {
          "step": 16,
          "fx": 0.18959999084472656,
          "fy": 0.0,
          "fz": 0.0
        },
        {
          "step": 17,
          "fx": 0.17836666107177734,
          "fy": -1.1444091796875e-05,
          "fz": -1.33514404296875e-05
        },
        {
          "step": 18,
          "fx": 0.16677093505859375,
          "fy": -4.1961669921875e-05,
          "fz": -3.719329833984375e-05
        },
        {
          "step": 19,
          "fx": 0.17615032196044922,
          "fy": -0.000102996826171875,
          "fz": -0.0001068115234375
        },
        {
          "step": 20,
          "fx": 0.16453933715820312,
          "fy": -0.000213623046875,
          "fz": -0.000213623046875
        }
      ],
      "wetted_area": 266.0,
      "dynamic_pressure": 0.4788,
      "evidence_status": "measured_candidate",
      "physical_validation": false,
      "steady_state": "diagnostic_withheld",
      "runtime": {
        "requested_steps": 20,
        "completed_steps": 20,
        "finite_population_checks": 20,
        "finite_density_checks": 20,
        "all_populations_finite": true,
        "all_densities_finite": true,
        "density_min": 0.9302381873130798,
        "density_max": 1.2105079889297485,
        "device": "cpu",
        "tau": 0.5216,
        "nu": 0.0072
      },
      "admission": {
        "status": "skipped",
        "reason": "use_wall_function=False; bounce-back solid boundary only, no wall function admitted"
      },
      "config": {
        "lattice": "D3Q19",
        "collision": "MRT",
        "boundary": "bounce_back",
        "wall": "static",
        "hull_type": "bare_hull",
        "nx": 64,
        "ny": 32,
        "nz": 32,
        "n_steps": 20,
        "warmup": 5,
        "u_in": 0.06,
        "re": 200.0,
        "hull_length": 24.0,
        "use_wall_function": false
      }
    },
    {
      "level_id": "domain_80",
      "nx": 80,
      "ny": 40,
      "nz": 40,
      "domain_length_lu": 80.0,
      "hull_length_lu": 24.0,
      "hull_radius_lu": 1.4002333722287048,
      "blockage_ratio": 0.0038497341384232447,
      "Ct": 0.4818580196979298,
      "ct_mean": 0.4818580196979298,
      "ct_time_series": [
        {
          "step": 1,
          "ct": 11.1111090909377,
          "ct_fric": 11.044495815722396,
          "ct_pres": 0.06661327521530369
        },
        {
          "step": 2,
          "ct": -3.7103472091406466,
          "ct_fric": -3.860204411353425,
          "ct_pres": 0.14985720221277812
        },
        {
          "step": 3,
          "ct": 1.924521536182919,
          "ct_fric": 1.7769982834323517,
          "ct_pres": 0.1475232527505675
        },
        {
          "step": 4,
          "ct": 1.0964519781269713,
          "ct_fric": 0.9701532616222697,
          "ct_pres": 0.12629871650470154
        },
        {
          "step": 5,
          "ct": -0.5426385896287853,
          "ct_fric": -0.6426405087172938,
          "ct_pres": 0.1000019190885085
        },
        {
          "step": 6,
          "ct": 2.1617361109891386,
          "ct_fric": 2.101836264502707,
          "ct_pres": 0.05989984648643162
        },
        {
          "step": 7,
          "ct": -0.285748764574766,
          "ct_fric": -0.3220347410661997,
          "ct_pres": 0.03628597649143373
        },
        {
          "step": 8,
          "ct": 0.5113344779498668,
          "ct_fric": 0.4925114883602762,
          "ct_pres": 0.018822989589590538
        },
        {
          "step": 9,
          "ct": 0.7813811588058656,
          "ct_fric": 0.7727301073186904,
          "ct_pres": 0.00865105148717511
        },
        {
          "step": 10,
          "ct": 0.14835362621157958,
          "ct_fric": 0.14158922134430338,
          "ct_pres": 0.006764404867276205
        },
        {
          "step": 11,
          "ct": 0.5971341967868576,
          "ct_fric": 0.5898945270661566,
          "ct_pres": 0.007239669720701082
        },
        {
          "step": 12,
          "ct": 0.3527489592798418,
          "ct_fric": 0.343734014527701,
          "ct_pres": 0.009014944752140774
        },
        {
          "step": 13,
          "ct": 0.3512257294689151,
          "ct_fric": 0.3402585462986423,
          "ct_pres": 0.010967183170272865
        },
        {
          "step": 14,
          "ct": 0.4698342080120084,
          "ct_fric": 0.45804422442539994,
          "ct_pres": 0.01178998358660846
        },
        {
          "step": 15,
          "ct": 0.32477051043491384,
          "ct_fric": 0.3123976629700878,
          "ct_pres": 0.012372847464825991
        },
        {
          "step": 16,
          "ct": 0.3936112546425262,
          "ct_fric": 0.3815130840579002,
          "ct_pres": 0.01209817058462605
        },
        {
          "step": 17,
          "ct": 0.3695588031832835,
          "ct_fric": 0.35776429512589386,
          "ct_pres": 0.011794508057389614
        },
        {
          "step": 18,
          "ct": 0.3455682910031838,
          "ct_fric": 0.33411544097734874,
          "ct_pres": 0.011452850025835085
        },
        {
          "step": 19,
          "ct": 0.3652764167145288,
          "ct_fric": 0.3540190318294114,
          "ct_pres": 0.0112573848851174
        },
        {
          "step": 20,
          "ct": 0.34108531656120417,
          "ct_fric": 0.3300160136100629,
          "ct_pres": 0.011069302951141323
        }
      ],
      "force_time_series": [
        {
          "step": 1,
          "fx": 5.559998989105225,
          "fy": 0.0,
          "fz": -1.9073486328125e-06
        },
        {
          "step": 2,
          "fx": -1.8566577434539795,
          "fy": 0.0,
          "fz": 1.9073486328125e-06
        },
        {
          "step": 3,
          "fx": 0.9630305767059326,
          "fy": 1.9073486328125e-06,
          "fz": -2.86102294921875e-06
        },
        {
          "step": 4,
          "fx": 0.5486645698547363,
          "fy": 1.9073486328125e-06,
          "fz": 1.9073486328125e-06
        },
        {
          "step": 5,
          "fx": -0.27153635025024414,
          "fy": 0.0,
          "fz": 1.9073486328125e-06
        },
        {
          "step": 6,
          "fx": 1.0817327499389648,
          "fy": 0.0,
          "fz": 0.0
        },
        {
          "step": 7,
          "fx": -0.1429886817932129,
          "fy": -1.9073486328125e-06,
          "fz": -9.5367431640625e-07
        },
        {
          "step": 8,
          "fx": 0.2558717727661133,
          "fy": 0.0,
          "fz": -1.9073486328125e-06
        },
        {
          "step": 9,
          "fx": 0.3910031318664551,
          "fy": 1.9073486328125e-06,
          "fz": -2.86102294921875e-06
        },
        {
          "step": 10,
          "fx": 0.07423615455627441,
          "fy": 1.9073486328125e-06,
          "fz": 3.814697265625e-06
        },
        {
          "step": 11,
          "fx": 0.29880595207214355,
          "fy": 1.9073486328125e-06,
          "fz": 1.9073486328125e-06
        },
        {
          "step": 12,
          "fx": 0.1765155792236328,
          "fy": 1.9073486328125e-06,
          "fz": 9.5367431640625e-07
        },
        {
          "step": 13,
          "fx": 0.17575335502624512,
          "fy": -1.9073486328125e-06,
          "fz": 0.0
        },
        {
          "step": 14,
          "fx": 0.23510503768920898,
          "fy": 0.0,
          "fz": 9.5367431640625e-07
        },
        {
          "step": 15,
          "fx": 0.16251516342163086,
          "fy": 0.0,
          "fz": 0.0
        },
        {
          "step": 16,
          "fx": 0.19696307182312012,
          "fy": -1.9073486328125e-06,
          "fz": 0.0
        },
        {
          "step": 17,
          "fx": 0.18492722511291504,
          "fy": 1.9073486328125e-06,
          "fz": 0.0
        },
        {
          "step": 18,
          "fx": 0.17292237281799316,
          "fy": 0.0,
          "fz": 9.5367431640625e-07
        },
        {
          "step": 19,
          "fx": 0.1827843189239502,
          "fy": -3.814697265625e-06,
          "fz": 9.5367431640625e-07
        },
        {
          "step": 20,
          "fx": 0.17067909240722656,
          "fy": -1.9073486328125e-06,
          "fz": -9.5367431640625e-07
        }
      ],
      "wetted_area": 278.0,
      "dynamic_pressure": 0.5004,
      "evidence_status": "measured_candidate",
      "physical_validation": false,
      "steady_state": "diagnostic_withheld",
      "runtime": {
        "requested_steps": 20,
        "completed_steps": 20,
        "finite_population_checks": 20,
        "finite_density_checks": 20,
        "all_populations_finite": true,
        "all_densities_finite": true,
        "density_min": 0.9302381873130798,
        "density_max": 1.2108780145645142,
        "device": "cpu",
        "tau": 0.5216,
        "nu": 0.0072
      },
      "admission": {
        "status": "skipped",
        "reason": "use_wall_function=False; bounce-back solid boundary only, no wall function admitted"
      },
      "config": {
        "lattice": "D3Q19",
        "collision": "MRT",
        "boundary": "bounce_back",
        "wall": "static",
        "hull_type": "bare_hull",
        "nx": 80,
        "ny": 40,
        "nz": 40,
        "n_steps": 20,
        "warmup": 5,
        "u_in": 0.06,
        "re": 200.0,
        "hull_length": 24.0,
        "use_wall_function": false
      }
    }
  ],
  "provenance": {
    "runner_api": "tensorlbm.suboff_validation_runner.run_suboff_d3q19_mrt_validation",
    "model_identity": {
      "lattice": "D3Q19",
      "collision": "MRT",
      "hull_type": "bare_hull",
      "boundary": "bounce_back",
      "wall": "static",
      "physics": "single_phase_incompressible"
    },
    "cad_source": "tensorlbm.suboff_cad.build_suboff_mask",
    "force_method": "d3q19_momentum_exchange",
    "ct_extraction": "mean_over_post_warmup_steps",
    "reference_area_mode": "voxel_wetted_area_lattice_units",
    "fixed_parameters": {
      "hull_length_lu": 24.0,
      "n_steps": 20,
      "warmup": 5,
      "u_in": 0.06,
      "re": 200.0,
      "grid_spacing_dx": 1.0
    },
    "prohibition": "no_convergence_claim_or_physical_validation"
  },
  "provenance_hash": "d9e9f2d35ae945f0051ecffd2e0c8d9e5c738ea9dee0c33c94413401dee829ca"
}
